pyfstab/__init__.py
pyfstab/entry.py
pyfstab/fstab.py
pyfstab-0.1.1.dist-info/LICENSE
pyfstab-0.1.1.dist-info/WHEEL
pyfstab-0.1.1.dist-info/METADATA
pyfstab-0.1.1.dist-info/RECORD
