Metadata-Version: 2.1
Name: pyfstab
Version: 0.1.1
Summary: Fstab parsing and formatting library
Home-page: https://github.com/b10011/pyfstab
License: MIT
Keywords: fstab,parser
Author: Niko Järvinen
Author-email: nbjarvinen@gmail.com
Requires-Python: >=3.5,<4.0
Classifier: Development Status :: 4 - Beta
Classifier: Intended Audience :: Developers
Classifier: Intended Audience :: System Administrators
Classifier: License :: OSI Approved :: MIT License
Classifier: Operating System :: POSIX
Classifier: Programming Language :: Python :: 3
Classifier: Programming Language :: Python :: 3.5
Classifier: Programming Language :: Python :: 3.6
Classifier: Programming Language :: Python :: 3.7
Classifier: Programming Language :: Python :: 3.8
Classifier: Topic :: Software Development :: Libraries
Classifier: Topic :: System :: Filesystems
Classifier: Topic :: System :: Operating System
Classifier: Topic :: Utilities
Project-URL: Documentation, https://pyfstab.readthedocs.io/en/latest/
Project-URL: Repository, https://github.com/b10011/pyfstab
